ahk/__main__.py
ahk/autostart.py
ahk/logs.py
ahk/main.py
ahk/paths.py
ahk/regenerate.py
ahk_resources/.gitignore
ahk_resources/procexp.exe
ahk_resources/regjump.exe
ahk_resources/toggle-icons.exe
ahk_resources/tool.ico
ahk_script_templates/WindowsTerminal.template.ahk
soda_ahk-2025.8.11.0.dist-info/METADATA
soda_ahk-2025.8.11.0.dist-info/WHEEL
soda_ahk-2025.8.11.0.dist-info/entry_points.txt
soda_ahk-2025.8.11.0.dist-info/licenses/LICENSE
soda_ahk-2025.8.11.0.dist-info/RECORD
