Metadata-Version: 2.4
Name: soda-ahk
Version: 2025.8.11.0
Summary: soda's ahk scripts
Project-URL: Repository, https://github.com/soda92/ahk
License-File: LICENSE
Requires-Python: >=3.10
Requires-Dist: hatchling>=1.27.0
Requires-Dist: pyinstaller>=6.15.0
